aimsChain/__init__.py
aimsChain/aimsio.py
aimsChain/atom.py
aimsChain/config.py
aimsChain/gs_path.py
aimsChain/interpolate.py
aimsChain/neb_path.py
aimsChain/node.py
aimsChain/path.py
aimsChain/string_path.py
aimsChain/utility.py
aimsChain/optimizer/__init__.py
aimsChain/optimizer/cg.py
aimsChain/optimizer/choleskybfgs.py
aimsChain/optimizer/dampedbfgs.py
aimsChain/optimizer/euler.py
aimsChain/optimizer/fire.py
aimsChain/optimizer/lbfgs.py
aimsChain/optimizer/newbfgs.py
aimsChain/optimizer/newfire.py
aimsChain/optimizer/optimize.py
aimsChain/optimizer/trmbfgs.py
aimsChain/tools/interpchain.py
aimsChain/tools/runchain.py
aims_chain-0.1.4.dist-info/LICENSE
aims_chain-0.1.4.dist-info/METADATA
aims_chain-0.1.4.dist-info/WHEEL
aims_chain-0.1.4.dist-info/entry_points.txt
aims_chain-0.1.4.dist-info/top_level.txt
aims_chain-0.1.4.dist-info/RECORD
