Metadata-Version: 2.2
Name: aims_chain
Version: 0.1.4
Summary: A package for finding minimum energy path and transition state.
License: This file ONLY applies to the code found in the "aimsChain" directory
Project-URL: repository, https://gitlab.com/FHI-aims-club/aims-chain
Requires-Python: >=3.10
License-File: LICENSE
Requires-Dist: numpy
Requires-Dist: scipy
Provides-Extra: test
Requires-Dist: pytest; extra == "test"
Requires-Dist: pytest-cov; extra == "test"
